plotvizard/__init__.py
plotvizard/data_processing.py
plotvizard/interactivity.py
plotvizard/plotting.py
plotvizard-0.1.1.dist-info/METADATA
plotvizard-0.1.1.dist-info/WHEEL
plotvizard-0.1.1.dist-info/entry_points.txt
plotvizard-0.1.1.dist-info/top_level.txt
plotvizard-0.1.1.dist-info/RECORD
